data_go_mcp/nps_business_enrollment/__init__.py
data_go_mcp/nps_business_enrollment/api_client.py
data_go_mcp/nps_business_enrollment/models.py
data_go_mcp/nps_business_enrollment/server.py
data_go_mcp_nps_business_enrollment-0.2.0.dist-info/METADATA
data_go_mcp_nps_business_enrollment-0.2.0.dist-info/WHEEL
data_go_mcp_nps_business_enrollment-0.2.0.dist-info/entry_points.txt
data_go_mcp_nps_business_enrollment-0.2.0.dist-info/licenses/LICENSE
data_go_mcp_nps_business_enrollment-0.2.0.dist-info/RECORD
