Metadata-Version: 2.4
Name: data-go-mcp.nps-business-enrollment
Version: 0.2.0
Summary: MCP server for Korea National Pension Service business enrollment API from data.go.kr
Project-URL: Homepage, https://github.com/Koomook/data-go-mcp-servers
Project-URL: Repository, https://github.com/Koomook/data-go-mcp-servers
Project-URL: Documentation, https://github.com/Koomook/data-go-mcp-servers/tree/main/src/nps-business-enrollment
Project-URL: Bug Tracker, https://github.com/Koomook/data-go-mcp-servers/issues
Project-URL: Changelog, https://github.com/Koomook/data-go-mcp-servers/blob/main/src/nps-business-enrollment/CHANGELOG.md
Author: Data.go.kr MCP Servers Contributors
License: Apache-2.0
License-File: LICENSE
Keywords: api,business,data.go.kr,enrollment,korea,mcp,nps,pension
Classifier: Development Status :: 3 - Alpha
Classifier: Intended Audience :: Developers
Classifier: License :: OSI Approved :: Apache Software License
Classifier: Programming Language :: Python :: 3
Classifier: Programming Language :: Python :: 3.10
Classifier: Programming Language :: Python :: 3.11
Classifier: Programming Language :: Python :: 3.12
Classifier: Programming Language :: Python :: 3.13
Requires-Python: >=3.10
Requires-Dist: httpx>=0.28.1
Requires-Dist: mcp[cli]>=1.13.0
Requires-Dist: pydantic>=2.11.7
Requires-Dist: python-dotenv>=1.1.1
